{
	"company": "Wham-O",
	"companyId": 67,
	"discs": [
	{
		"discId": 1,
		"name": "Touchline Under",
		"type": "D",
		"range": 366,
		"hst": -38,
		"lsf": 38
	},	{
		"discId": 2,
		"name": "Touchline Putter",
		"type": "P",
		"range": 235,
		"hst": -36,
		"lsf": 18
	},	{
		"discId": 3,
		"name": "Touchline Over",
		"type": "F",
		"range": 335,
		"hst": -28,
		"lsf": 47
	},	{
		"discId": 4,
		"name": "Touchline Bank",
		"type": "F",
		"range": 279,
		"hst": -36,
		"lsf": 36
	},	{
		"discId": 5,
		"name": "Voyager",
		"type": "F",
		"range": 347,
		"hst": -38,
		"lsf": 19
	},	{
		"discId": 6,
		"name": "86 Softie",
		"type": "P",
		"range": 232,
		"hst": -36,
		"lsf": 18
	},	{
		"discId": 7,
		"name": "Fairway Driver",
		"type": "F",
		"range": 312,
		"hst": -28,
		"lsf": 18
	},	{
		"discId": 8,
		"name": "Touchline True",
		"type": "M",
		"range": 280,
		"hst": -18,
		"lsf": 36
	},	{
		"discId": 9,
		"name": "Mid Range Approach",
		"type": "M",
		"range": 268,
		"hst": -4,
		"lsf": 27
	},	{
		"discId": 10,
		"name": "Putter",
		"type": "P",
		"range": 248,
		"hst": 0,
		"lsf": 18
	}]
}

	